sampleids/__init__.py
sampleids/id.py
sampleids/normalize.py
sampleids/parse.py
sampleids-0.0.2.dist-info/LICENSE
sampleids-0.0.2.dist-info/METADATA
sampleids-0.0.2.dist-info/WHEEL
sampleids-0.0.2.dist-info/top_level.txt
sampleids-0.0.2.dist-info/RECORD
